csvtea/__init__.py
csvtea/adapter.py
csvtea/cell.py
csvtea/csvparser.py
csvtea/format.py
csvtea_elunico-3.0.2.dist-info/METADATA
csvtea_elunico-3.0.2.dist-info/WHEEL
csvtea_elunico-3.0.2.dist-info/top_level.txt
csvtea_elunico-3.0.2.dist-info/RECORD
