Metadata-Version: 2.1
Name: csvtea-elunico
Version: 3.0.2
Summary: A flexible, extensible, pluggable, slightly-out-of-spec CSV parser
Home-page: https://github.com/elunico/CSVTea
Author: Thomas Povinelli
Author-email: tompov227@gmail.com
License: UNKNOWN
Platform: UNKNOWN
Classifier: Programming Language :: Python :: 3
Classifier: License :: OSI Approved :: MIT License
Classifier: Operating System :: OS Independent
Requires-Python: >=3.6
